Metadata-Version: 1.0
Name: PyBarLoad
Version: 1.1.2
Summary: Le module PyBarLoad est un module, qui permet de faire des barres de chargements ! ( Personalisables ! + Ajout de couleurs ) 
Home-page: UNKNOWN
Author: UNKNOWN
Author-email: <Maxencedu62_@outlook.fr>
License: MIT
Keywords: python,Loading Bar,loadBar,BarLoad,PyBarLoad
Platform: UNKNOWN
